adafruit_scd30.py
adafruit_circuitpython_scd30-2.2.17.dist-info/licenses/LICENSE
adafruit_circuitpython_scd30-2.2.17.dist-info/METADATA
adafruit_circuitpython_scd30-2.2.17.dist-info/WHEEL
adafruit_circuitpython_scd30-2.2.17.dist-info/top_level.txt
adafruit_circuitpython_scd30-2.2.17.dist-info/RECORD
